SD/APS4/control_unit.v
module control_unit 
    (output reg IR_Load, 
     output reg MAR_Load, 
     output reg PC_Load, PC_Inc, 
     output reg A_Load, B_Load,
     output reg CCR_Load,
     output reg [2:0] ALU_Sel,
     output reg [1:0] Bus1_Sel, Bus2_Sel,
     output reg write, 
     input wire [7:0] IR, 
     input wire [3:0] CCR_Result,
     input wire Clk, Reset);
             
    reg [7:0] current_state, next_state;

    // parâmetros de estado
    parameter S0_FETCH = 8'd0,  //opcode de estados de busca (fetch)
              S1_FETCH = 8'd1,
              S2_FETCH = 8'd2,
              
              S3_DECODE = 8'd3, //opcode de estado de decodificação (decode)
              
              S4_LDA_IMM = 8'd4, //LDA_IMM = load A immediate ; estados de execução
              S5_LDA_IMM = 8'd5,
              S6_LDA_IMM = 8'd6,
              
              S4_LDA_DIR = 8'd7, //LDA_DIR = load A direct ; estados de execução
              S5_LDA_DIR = 8'd8,
              S6_LDA_DIR = 8'd9,
              S7_LDA_DIR = 8'd10,
              S8_LDA_DIR = 8'd11,

              S4_STA_DIR = 8'd12, // store A direct ; estados de execução
              S5_STA_DIR = 8'd13,
              S6_STA_DIR = 8'd14,
              
              S4_ADD_IMM = 8'd15, // add immediate to A ; estados de execução
              S5_ADD_IMM = 8'd16,
              S6_ADD_IMM = 8'd17;
              
    // definições de opcode 
    parameter [7:0] LDA_IMM = 8'h01; // load A immediate
    parameter [7:0] LDA_DIR = 8'h02; // load A direct
    parameter [7:0] STA_DIR = 8'h12; // store A direct
    parameter [7:0] ADD_IMM = 8'h21; // add immediate to A
              
    // códigos de seleção de bus
    // Bus1_Sel: 00 = PC, 01 = A, 10 = B 
    parameter [1:0] SEL_PC = 2'b00;
    parameter [1:0] SEL_A  = 2'b01;
    parameter [1:0] SEL_B  = 2'b10;
    
    // Bus2_Sel: 00 = ALU, 01 = Bus1, 10 = from_memory 
    parameter [1:0] SEL_ALU = 2'b00;
    parameter [1:0] SEL_BUS1 = 2'b01;
    parameter [1:0] SEL_MEM  = 2'b10;

    // códigos de seleção da ULA
    // ALU_Sel: 000 = ADD, 001 = SUB, 010 = PASS_B 
    parameter [2:0] ALU_ADD = 3'b000;
    parameter [2:0] ALU_PASS_B = 3'b010; // dados de B para o bus/A
    parameter [2:0] ALU_INC = 3'b111; // PC_Inc (PC=PC+1)

    initial
        begin
            current_state = S0_FETCH;
            next_state = S0_FETCH;
            IR_Load = 0;
            MAR_Load = 0;
            PC_Load = 0;
            PC_Inc = 0;
            A_Load = 0;
            B_Load = 0;
            CCR_Load = 0;
            ALU_Sel = ALU_PASS_B; 
            Bus1_Sel = SEL_PC; 
            Bus2_Sel = SEL_BUS1; 
            write = 0;
        end 

    // bloco de memória de estado
    always @ (posedge Clk or negedge Reset)
        begin: STATE_MEMORY
            if (!Reset)
                current_state <= S0_FETCH;
            else
                current_state <= next_state;
        end

    // bloco de lógica do próximo estado
    always @ (current_state, IR)
        begin: NEXT_STATE_LOGIC
            next_state = S0_FETCH; // transição padrão
            case (current_state)
                S0_FETCH : next_state = S1_FETCH;
                S1_FETCH : next_state = S2_FETCH;
                S2_FETCH : next_state = S3_DECODE;
                
                S3_DECODE : 
                    begin 
                        case (IR)
                            LDA_IMM: next_state = S4_LDA_IMM;
                            LDA_DIR: next_state = S4_LDA_DIR;
                            STA_DIR: next_state = S4_STA_DIR;
                            ADD_IMM: next_state = S4_ADD_IMM;
                            default: next_state = S0_FETCH; 
                        endcase
                    end
            
                // sequência LDA_IMM 
                S4_LDA_IMM : next_state = S5_LDA_IMM; // operando vai para o MAR
                S5_LDA_IMM : next_state = S6_LDA_IMM; // carregar A
                S6_LDA_IMM : next_state = S0_FETCH;   // fim
                                     
                // sequência LDA_DIR
                S4_LDA_DIR : next_state = S5_LDA_DIR; // LSB do endereço vai para o MAR
                S5_LDA_DIR : next_state = S6_LDA_DIR; // incrementa PC
                S6_LDA_DIR : next_state = S7_LDA_DIR; // MSB do endereço vai para o MAR (upper bits of MAR)
                S7_LDA_DIR : next_state = S8_LDA_DIR; // busca de dados para B
                S8_LDA_DIR : next_state = S0_FETCH;   // carregar A e finalizar

                // sequência STA_DIR 
                S4_STA_DIR : next_state = S5_STA_DIR; // LSB do endereço vai para o MAR
                S5_STA_DIR : next_state = S6_STA_DIR; // incrementa PC, MSB para MAR
                S6_STA_DIR : next_state = S0_FETCH;   // escrever A em endereço de memória

                // sequência ADD_IMM
                S4_ADD_IMM : next_state = S5_ADD_IMM; // operando vai para MAR
                S5_ADD_IMM : next_state = S6_ADD_IMM; // carregar B
                S6_ADD_IMM : next_state = S0_FETCH;   // ADD A+B -> A
                
                default : next_state = S0_FETCH;
            endcase
        end

    // bloco de lógica do output
    always @ (current_state)
        begin: OUTPUT_LOGIC
            // valores padrão para sinais de controle
            IR_Load = 0;
            MAR_Load = 0;
            PC_Load = 0;
            PC_Inc = 0;
            A_Load = 0;
            B_Load = 0;
            CCR_Load = 0;
            write = 0;
            Bus1_Sel = SEL_PC;     
            Bus2_Sel = SEL_BUS1;    
            ALU_Sel = ALU_PASS_B;   

            case (current_state)
                
                // FETCH CYCLE
                S0_FETCH : 
                    begin // MAR <- PC
                        MAR_Load = 1;
                        Bus1_Sel = SEL_PC; 
                        Bus2_Sel = SEL_BUS1; 
                    end
                    
                S1_FETCH : 
                    begin // PC <- PC + 1
                        PC_Inc = 1;
                        Bus1_Sel = SEL_PC; // PC input para ALU
                        Bus2_Sel = SEL_BUS1; 
                        ALU_Sel = ALU_INC; // ALU faz +1
                    end
                    
                S2_FETCH : 
                    begin // carregar registro de instruções (IR <- M[MAR])
                        IR_Load = 1;
                        Bus1_Sel = SEL_PC; // don't care
                        Bus2_Sel = SEL_MEM; // M[MAR] para Main Bus
                    end
                
                S3_DECODE : 
                    begin // decode: sem operações necessárias
                    end

                // LDA_IMM 
                // instrução: [OPCODE] [DATA]
                S4_LDA_IMM : 
                    begin // MAR <- PC
                        MAR_Load = 1;
                        Bus1_Sel = SEL_PC; 
                        Bus2_Sel = SEL_BUS1; 
                    end
                S5_LDA_IMM : 
                    begin // PC <- PC + 1
                        PC_Inc = 1;
                        Bus1_Sel = SEL_PC; 
                        Bus2_Sel = SEL_BUS1; 
                        ALU_Sel = ALU_INC; 
                    end
                S6_LDA_IMM : 
                    begin // A <- M[MAR]
                        A_Load = 1;
                        Bus2_Sel = SEL_MEM; // M[MAR] para Main Bus
                    end

                // LDA_DIR 
                // instrução: [OPCODE] [ADDR_LSB] [ADDR_MSB] (2-byte address)
                S4_LDA_DIR : 
                    begin // MAR <- PC
                        MAR_Load = 1; 
                        Bus1_Sel = SEL_PC; 
                        Bus2_Sel = SEL_BUS1; 
                    end
                S5_LDA_DIR : 
                    begin // incrementa PC and put LSB of address into MAR LSB
                        PC_Inc = 1;
                        Bus1_Sel = SEL_PC; 
                        Bus2_Sel = SEL_BUS1; 
                        ALU_Sel = ALU_INC; 
                    end
                S6_LDA_DIR : 
                    begin // leva o MSB do endereço para o MSB do MAR
                        MAR_Load = 1; // carrega MAR (MSB)
                        Bus2_Sel = SEL_MEM; // M[MAR] (ADDR_LSB) para MAR (upper bits)
                    end
                S7_LDA_DIR : 
                    begin // busca de dados para B
                        B_Load = 1;
                        Bus2_Sel = SEL_MEM; // M[MAR] (Data) para B
                    end
                S8_LDA_DIR : 
                    begin // A <- B
                        A_Load = 1;
                        Bus1_Sel = SEL_B;
                        Bus2_Sel = SEL_BUS1; 
                    end

                // STA_DIR 
                // instrução: [OPCODE] [ADDR_LSB] [ADDR_MSB]
                S4_STA_DIR : 
                    begin // MAR <- PC
                        MAR_Load = 1; 
                        Bus1_Sel = SEL_PC; 
                        Bus2_Sel = SEL_BUS1; 
                    end
                S5_STA_DIR : 
                    begin // incrementa PC e leva o MSB do endereço para o MSB do MAR
                        PC_Inc = 1;
                        MAR_Load = 1; 
                        Bus2_Sel = SEL_MEM; 
                        ALU_Sel = ALU_INC;
                    end
                S6_STA_DIR : 
                    begin // M[MAR] <- A
                        write = 1;
                        Bus1_Sel = SEL_A; // A para o bus de dados da memória
                        Bus2_Sel = SEL_BUS1; 
                    end

                // ADD_IMM 
                // instrução: [OPCODE] [DATA]
                S4_ADD_IMM : 
                    begin // MAR <- PC (LSB)
                        MAR_Load = 1;
                        Bus1_Sel = SEL_PC; 
                        Bus2_Sel = SEL_BUS1; 
                    end
                S5_ADD_IMM : 
                    begin // incrementa PC and carrega B (B <- M[MAR])
                        PC_Inc = 1; 
                        B_Load = 1; 
                        Bus2_Sel = SEL_MEM; // M[MAR] para B
                        ALU_Sel = ALU_INC; 
                    end
                S6_ADD_IMM : 
                    begin // A <- A + B
                        A_Load = 1;
                        CCR_Load = 1; // atualizando codigos de condição
                        Bus1_Sel = SEL_A; // A vai para ALU input
                        ALU_Sel = ALU_ADD; // A+B 
                        Bus2_Sel = SEL_ALU; // resultado da ALU vai para o registro de A
                    end
                
                default : 
                    begin
                    end
            endcase
        end
        
endmodule

SD/APS4/control_unit_tb.v
`timescale 1ns/1ps
`include "control_unit.v"

module control_unit_tb;

    // sinais para a Unidade de Controle
    reg Clk = 1'b0;
    reg Reset = 1'b0;
    reg [7:0] IR_in = 8'h00; // simula a saída do registrador IR (entrada para a UC)
    reg [3:0] CCR_Result_in = 4'b0000;

    // saídas da Unidade de Controle 
    wire IR_Load, MAR_Load, PC_Load, PC_Inc;
    wire A_Load, B_Load, CCR_Load;
    wire [2:0] ALU_Sel;
    wire [1:0] Bus1_Sel, Bus2_Sel;
    wire write; 

    // instanciação device under test
    control_unit dut (
        .IR_Load(IR_Load), 
        .MAR_Load(MAR_Load), 
        .PC_Load(PC_Load), 
        .PC_Inc(PC_Inc), 
        .A_Load(A_Load), 
        .B_Load(B_Load),
        .CCR_Load(CCR_Load),
        .ALU_Sel(ALU_Sel),
        .Bus1_Sel(Bus1_Sel), 
        .Bus2_Sel(Bus2_Sel),
        .write(write),
        .IR(IR_in), 
        .CCR_Result(CCR_Result_in), 
        .Clk(Clk), 
        .Reset(Reset)
    );

    // geração do clock (50% duty cycle, 20ns period)
    always #10 Clk = ~Clk;

    initial begin
        $dumpfile("control_unit_tb.vcd");
        $dumpvars(0, control_unit_tb);

        // reset
        Reset = 1'b0;
        #20 Reset = 1'b1; // reset assíncrono ativo baixo
        
        // IR_in deve ser forçado com o opcode correto apenas no final de S2_FETCH

        // TESTE 1: LDA_IMM (Load A Immediate - Opcode 8'h01)
        // duração: 3 fetch + 3 execute = 6 ciclos

        // C1 (S0_FETCH)
        @(posedge Clk); IR_in = 8'h00;
        // C2 (S1_FETCH)
        @(posedge Clk);
        // C3 (S2_FETCH): IR <- M[MAR]
        @(posedge Clk); IR_in = 8'h01; // Força IR=LDA_IMM
        // C4 (S3_DECODE)
        @(posedge Clk); 
        
        // EXECUÇÃO LDA_IMM
        // C5 (S4_LDA_IMM)
        @(posedge Clk);
        // C6 (S5_LDA_IMM)
        @(posedge Clk);
        // C7 (S6_LDA_IMM)
        @(posedge Clk); 

        // TESTE 2: ADD_IMM (Add Immediate - Opcode 8'h21)
        // duração: 3 fetch + 3 execute = 6 ciclos

        // C8 (S0_FETCH)
        @(posedge Clk); IR_in = 8'h00;
        // C9 (S1_FETCH)
        @(posedge Clk);
        // C10 (S2_FETCH): IR <- M[MAR]
        @(posedge Clk); IR_in = 8'h21; // força IR=ADD_IMM 
        // C11 (S3_DECODE)
        @(posedge Clk); 
        
        // EXECUÇÃO ADD_IMM
        // C12 (S4_ADD_IMM)
        @(posedge Clk);
        // C13 (S5_ADD_IMM)
        @(posedge Clk);
        // C14 (S6_ADD_IMM)
        @(posedge Clk);

        // TESTE 3: STA_DIR (Store A Direct - Opcode 8'h12)
        // duração: 3 fetch + 3 execute = 6 ciclos
        
        // C15 (S0_FETCH)
        @(posedge Clk); IR_in = 8'h00; 
        // C16 (S1_FETCH)
        @(posedge Clk);
        // C17 (S2_FETCH): IR <- M[MAR]
        @(posedge Clk); IR_in = 8'h12; // força IR=STA_DIR 
        // C18 (S3_DECODE)
        @(posedge Clk); 
        
        // EXECUÇÃO STA_DIR
        // C19 (S4_STA_DIR)
        @(posedge Clk);
        // C20 (S5_STA_DIR)
        @(posedge Clk);
        // C21 (S6_STA_DIR): o sinal 'write' deve ser ativado neste ciclo!
        @(posedge Clk);

        // TESTE 4: LDA_DIR (Load A Direct - opcode 8'h02)
        // duração: 3 fetch + 5 execute = 8 ciclos

        // C22 (S0_FETCH)
        @(posedge Clk); IR_in = 8'h00; 
        // C23 (S1_FETCH)
        @(posedge Clk);
        // C24 (S2_FETCH): IR <- M[MAR] 
        @(posedge Clk); IR_in = 8'h02; // força IR=LDA_DIR 
        // C25 (S3_DECODE)
        @(posedge Clk);
        
        // EXECUÇÃO LDA_DIR 
        // C26 (S4_LDA_DIR)
        @(posedge Clk);
        // C27 (S5_LDA_DIR)
        @(posedge Clk);
        // C28 (S6_LDA_DIR)
        @(posedge Clk);
        // C29 (S7_LDA_DIR)
        @(posedge Clk);
        // C30 (S8_LDA_DIR)
        @(posedge Clk);

        #50 $finish; 
    end

endmodule

SD/APS4/control_unit_tb.vcd
$date
	Tue Dec 16 23:34:47 2025
$end
$version
	Icarus Verilog
$end
$timescale
	1ps
$end
$scope module control_unit_tb $end
$var wire 1 ! write $end
$var wire 1 " PC_Load $end
$var wire 1 # PC_Inc $end
$var wire 1 $ MAR_Load $end
$var wire 1 % IR_Load $end
$var wire 1 & CCR_Load $end
$var wire 2 ' Bus2_Sel [1:0] $end
$var wire 2 ( Bus1_Sel [1:0] $end
$var wire 1 ) B_Load $end
$var wire 1 * A_Load $end
$var wire 3 + ALU_Sel [2:0] $end
$var reg 4 , CCR_Result_in [3:0] $end
$var reg 1 - Clk $end
$var reg 8 . IR_in [7:0] $end
$var reg 1 / Reset $end
$scope module dut $end
$var wire 4 0 CCR_Result [3:0] $end
$var wire 1 - Clk $end
$var wire 8 1 IR [7:0] $end
$var wire 1 / Reset $end
$var parameter 8 2 ADD_IMM $end
$var parameter 3 3 ALU_ADD $end
$var parameter 3 4 ALU_INC $end
$var parameter 3 5 ALU_PASS_B $end
$var parameter 8 6 LDA_DIR $end
$var parameter 8 7 LDA_IMM $end
$var parameter 8 8 S0_FETCH $end
$var parameter 8 9 S1_FETCH $end
$var parameter 8 : S2_FETCH $end
$var parameter 8 ; S3_DECODE $end
$var parameter 8 < S4_ADD_IMM $end
$var parameter 8 = S4_LDA_DIR $end
$var parameter 8 > S4_LDA_IMM $end
$var parameter 8 ? S4_STA_DIR $end
$var parameter 8 @ S5_ADD_IMM $end
$var parameter 8 A S5_LDA_DIR $end
$var parameter 8 B S5_LDA_IMM $end
$var parameter 8 C S5_STA_DIR $end
$var parameter 8 D S6_ADD_IMM $end
$var parameter 8 E S6_LDA_DIR $end
$var parameter 8 F S6_LDA_IMM $end
$var parameter 8 G S6_STA_DIR $end
$var parameter 8 H S7_LDA_DIR $end
$var parameter 8 I S8_LDA_DIR $end
$var parameter 2 J SEL_A $end
$var parameter 2 K SEL_ALU $end
$var parameter 2 L SEL_B $end
$var parameter 2 M SEL_BUS1 $end
$var parameter 2 N SEL_MEM $end
$var parameter 2 O SEL_PC $end
$var parameter 8 P STA_DIR $end
$var reg 3 Q ALU_Sel [2:0] $end
$var reg 1 * A_Load $end
$var reg 1 ) B_Load $end
$var reg 2 R Bus1_Sel [1:0] $end
$var reg 2 S Bus2_Sel [1:0] $end
$var reg 1 & CCR_Load $end
$var reg 1 % IR_Load $end
$var reg 1 $ MAR_Load $end
$var reg 1 # PC_Inc $end
$var reg 1 " PC_Load $end
$var reg 8 T current_state [7:0] $end
$var reg 8 U next_state [7:0] $end
$var reg 1 ! write $end
$scope begin NEXT_STATE_LOGIC $end
$upscope $end
$scope begin OUTPUT_LOGIC $end
$upscope $end
$scope begin STATE_MEMORY $end
$upscope $end
$upscope $end
$upscope $end
$enddefinitions $end
$comment Show the parameter values. $end
$dumpall
b10010 P
b0 O
b10 N
b1 M
b10 L
b0 K
b1 J
b1011 I
b1010 H
b1110 G
b110 F
b1001 E
b10001 D
b1101 C
b101 B
b1000 A
b10000 @
b1100 ?
b100 >
b111 =
b1111 <
b11 ;
b10 :
b1 9
b0 8
b1 7
b10 6
b10 5
b111 4
b0 3
b100001 2
$end
#0
$dumpvars
b1 U
b0 T
b1 S
b0 R
b10 Q
b0 1
b0 0
0/
b0 .
0-
b0 ,
b10 +
0*
0)
b0 (
b1 '
0&
0%
1$
0#
0"
0!
$end
#10000
1-
#20000
0-
1/
#30000
b111 +
b111 Q
1#
0$
b10 U
b1 T
1-
#40000
0-
#50000
b10 '
b10 S
1%
b10 +
b10 Q
0#
b11 U
b10 T
1-
#60000
0-
#70000
b1 '
b1 S
0%
b11 T
b100 U
b1 .
b1 1
1-
#80000
0-
#90000
1$
b101 U
b100 T
1-
#100000
0-
#110000
b111 +
b111 Q
1#
0$
b110 U
b101 T
1-
#120000
0-
#130000
b10 '
b10 S
1*
b10 +
b10 Q
0#
b0 U
b110 T
1-
#140000
0-
#150000
1$
b1 '
b1 S
0*
b1 U
b0 T
1-
#160000
0-
#170000
b111 +
b111 Q
1#
0$
b1 T
b10 U
b0 .
b0 1
1-
#180000
0-
#190000
b10 '
b10 S
1%
b10 +
b10 Q
0#
b11 U
b10 T
1-
#200000
0-
#210000
b1 '
b1 S
0%
b11 T
b1111 U
b100001 .
b100001 1
1-
#220000
0-
#230000
1$
b10000 U
b1111 T
1-
#240000
0-
#250000
b111 +
b111 Q
b10 '
b10 S
1)
1#
0$
b10001 U
b10000 T
1-
#260000
0-
#270000
b1 (
b1 R
1&
1*
b0 +
b0 Q
b0 '
b0 S
0)
0#
b0 U
b10001 T
1-
#280000
0-
#290000
1$
b10 +
b10 Q
b1 '
b1 S
b0 (
b0 R
0&
0*
b1 U
b0 T
1-
#300000
0-
#310000
b111 +
b111 Q
1#
0$
b1 T
b10 U
b0 .
b0 1
1-
#320000
0-
#330000
b10 '
b10 S
1%
b10 +
b10 Q
0#
b11 U
b10 T
1-
#340000
0-
#350000
b1 '
b1 S
0%
b11 T
b1100 U
b10010 .
b10010 1
1-
#360000
0-
#370000
1$
b1101 U
b1100 T
1-
#380000
0-
#390000
b111 +
b111 Q
b10 '
b10 S
1#
1$
b1110 U
b1101 T
1-
#400000
0-
#410000
b1 (
b1 R
1!
b10 +
b10 Q
b1 '
b1 S
0#
0$
b0 U
b1110 T
1-
#420000
0-
#430000
1$
b0 (
b0 R
0!
b1 U
b0 T
1-
#440000
0-
#450000
b111 +
b111 Q
1#
0$
b1 T
b10 U
b0 .
b0 1
1-
#460000
0-
#470000
b10 '
b10 S
1%
b10 +
b10 Q
0#
b11 U
b10 T
1-
#480000
0-
#490000
b1 '
b1 S
0%
b11 T
b111 U
b10 .
b10 1
1-
#500000
0-
#510000
1$
b1000 U
b111 T
1-
#520000
0-
#530000
b111 +
b111 Q
1#
0$
b1001 U
b1000 T
1-
#540000
0-
#550000
b10 '
b10 S
1$
b10 +
b10 Q
0#
b1010 U
b1001 T
1-
#560000
0-
#570000
1)
b10 '
b10 S
0$
b1011 U
b1010 T
1-
#580000
0-
#590000
b10 (
b10 R
1*
b1 '
b1 S
0)
b0 U
b1011 T
1-
#600000
0-
#610000
1$
b0 (
b0 R
0*
b1 U
b0 T
1-
#620000
0-
#630000
b111 +
b111 Q
1#
0$
b10 U
b1 T
1-
#640000
0-
#650000
b10 '
b10 S
1%
b10 +
b10 Q
0#
b11 U
b10 T
1-
